piper_sdk/__init__.py
piper_sdk/client.py
pyper_sdk-0.7.1.dist-info/licenses/LICENSE
pyper_sdk-0.7.1.dist-info/METADATA
pyper_sdk-0.7.1.dist-info/WHEEL
pyper_sdk-0.7.1.dist-info/top_level.txt
pyper_sdk-0.7.1.dist-info/RECORD
