Metadata-Version: 2.4
Name: pyper-sdk
Version: 0.7.1
Summary: Python SDK for Piper Agent Credential Management. Secure, flexible, and simple.
Home-page: https://github.com/greylab0/piper-python-sdk
Author: Piper
Author-email: devs@agentpiper.com
Project-URL: Documentation, https://github.com/greylab0/piper-python-sdk/blob/main/README.md
Project-URL: Source, https://github.com/greylab0/piper-python-sdk
Project-URL: Tracker, https://github.com/greylab0/piper-python-sdk/issues
Keywords: piper credentials secrets sdk agent gcp sts mcp llm api key
Classifier: Programming Language :: Python :: 3
Classifier: Programming Language :: Python :: 3.7
Classifier: Programming Language :: Python :: 3.8
Classifier: Programming Language :: Python :: 3.9
Classifier: Programming Language :: Python :: 3.10
Classifier: Programming Language :: Python :: 3.11
Classifier: License :: OSI Approved :: MIT License
Classifier: Operating System :: OS Independent
Classifier: Development Status :: 4 - Beta
Classifier: Intended Audience :: Developers
Classifier: Topic :: Software Development :: Libraries :: Python Modules
Classifier: Topic :: Security
Requires-Python: >=3.7
License-File: LICENSE
Requires-Dist: requests>=2.20.0
Dynamic: author
Dynamic: author-email
Dynamic: classifier
Dynamic: description
Dynamic: description-content-type
Dynamic: home-page
Dynamic: keywords
Dynamic: license-file
Dynamic: project-url
Dynamic: requires-dist
Dynamic: requires-python
Dynamic: summary
